obp/__init__.py
obp/types.py
obp/utils.py
obp/version.py
obp/dataset/__init__.py
obp/dataset/base.py
obp/dataset/multiclass.py
obp/dataset/real.py
obp/dataset/reward_type.py
obp/dataset/synthetic.py
obp/dataset/synthetic_slate.py
obp/dataset/obd/.DS_Store
obp/dataset/obd/bts/.DS_Store
obp/dataset/obd/bts/all/.DS_Store
obp/dataset/obd/bts/all/all.csv
obp/dataset/obd/bts/all/item_context.csv
obp/dataset/obd/bts/men/.DS_Store
obp/dataset/obd/bts/men/item_context.csv
obp/dataset/obd/bts/men/men.csv
obp/dataset/obd/bts/women/.DS_Store
obp/dataset/obd/bts/women/item_context.csv
obp/dataset/obd/bts/women/women.csv
obp/dataset/obd/random/.DS_Store
obp/dataset/obd/random/all/.DS_Store
obp/dataset/obd/random/all/all.csv
obp/dataset/obd/random/all/item_context.csv
obp/dataset/obd/random/men/.DS_Store
obp/dataset/obd/random/men/item_context.csv
obp/dataset/obd/random/men/men.csv
obp/dataset/obd/random/women/.DS_Store
obp/dataset/obd/random/women/item_context.csv
obp/dataset/obd/random/women/women.csv
obp/ope/__init__.py
obp/ope/estimators.py
obp/ope/estimators_slate.py
obp/ope/meta.py
obp/ope/meta_slate.py
obp/ope/regression_model.py
obp/policy/__init__.py
obp/policy/base.py
obp/policy/contextfree.py
obp/policy/linear.py
obp/policy/logistic.py
obp/policy/offline.py
obp/policy/policy_type.py
obp/policy/conf/prior_bts.yaml
obp/simulator/__init__.py
obp/simulator/simulator.py
obp-0.4.1.dist-info/LICENSE
obp-0.4.1.dist-info/METADATA
obp-0.4.1.dist-info/WHEEL
obp-0.4.1.dist-info/top_level.txt
obp-0.4.1.dist-info/RECORD
