Metadata-Version: 2.1
Name: obp
Version: 0.4.1
Summary: Open Bandit Pipeline: a python library for bandit algorithms and off-policy evaluation
Home-page: https://github.com/st-tech/zr-obp
Author: Yuta Saito
Author-email: open-bandit-project@googlegroups.com
License: Apache License
Keywords: bandit algorithms,off-policy evaluation
Platform: UNKNOWN
Classifier: Topic :: Scientific/Engineering :: Artificial Intelligence
Classifier: Intended Audience :: Science/Research
Classifier: Programming Language :: Python :: 3.7
Classifier: Programming Language :: Python :: 3.8
Classifier: License :: OSI Approved :: Apache Software License
Requires-Dist: matplotlib (>=3.2.2)
Requires-Dist: mypy-extensions (>=0.4.3)
Requires-Dist: numpy (>=1.18.1)
Requires-Dist: pandas (>=0.25.1)
Requires-Dist: pyyaml (>=5.1)
Requires-Dist: seaborn (>=0.10.1)
Requires-Dist: scikit-learn (>=0.23.1)
Requires-Dist: scipy (>=1.4.1)
Requires-Dist: torch (>=1.7.1)
Requires-Dist: tqdm (>=4.41.1)
